shortfuse/__init__.py
shortfuse_lib-0.1.0.dist-info/licenses/LICENSE
shortfuse_lib-0.1.0.dist-info/METADATA
shortfuse_lib-0.1.0.dist-info/WHEEL
shortfuse_lib-0.1.0.dist-info/top_level.txt
shortfuse_lib-0.1.0.dist-info/RECORD
