Metadata-Version: 2.4
Name: shortfuse-lib
Version: 0.1.0
Summary: Don't just raise exceptions—kill the process. A fail-fast library for laying traps in forbidden code paths.
Author-email: Larry Richards <your-email@example.com>
License: MIT License
Project-URL: Homepage, https://github.com/lbrichards/shortfuse
Project-URL: Bug Tracker, https://github.com/lbrichards/shortfuse/issues
Classifier: Programming Language :: Python :: 3
Classifier: License :: OSI Approved :: MIT License
Classifier: Operating System :: OS Independent
Classifier: Topic :: Software Development :: Debuggers
Classifier: Topic :: Software Development :: Quality Assurance
Requires-Python: >=3.7
License-File: LICENSE
Provides-Extra: dev
Requires-Dist: pytest>=7.0; extra == "dev"
Requires-Dist: build; extra == "dev"
Requires-Dist: twine; extra == "dev"
Requires-Dist: pdoc; extra == "dev"
Dynamic: license-file
